netbox_cvexplorer/__init__.py
netbox_cvexplorer/info.json
netbox_cvexplorer/navigation.py
netbox_cvexplorer/urls.py
netbox_cvexplorer/migrations/0001_initial.py
netbox_cvexplorer/migrations/__init__.py
netbox_cvexplorer/models/__init__.py
netbox_cvexplorer/models/cve.py
netbox_cvexplorer/tables/__init__.py
netbox_cvexplorer/tables/cve.py
netbox_cvexplorer/templates/netbox_cvexplorer/cve_list.html
netbox_cvexplorer/views/__init__.py
netbox_cvexplorer/views/cve.py
netbox_cvexplorer-1.0.17.dist-info/licenses/LICENSE
netbox_cvexplorer-1.0.17.dist-info/METADATA
netbox_cvexplorer-1.0.17.dist-info/WHEEL
netbox_cvexplorer-1.0.17.dist-info/top_level.txt
netbox_cvexplorer-1.0.17.dist-info/RECORD
