Metadata-Version: 2.4
Name: netbox-cvexplorer
Version: 1.0.17
Summary: NetBox Plugin zur Anzeige und Verwaltung von CVE-Informationen
Author-email: Tino Schiffel <tino.schiffel@billhost.de>
License: MIT
Project-URL: Homepage, https://localrespository/netbox-cvexplorer
Project-URL: Source, https://localrespository/netbox-cvexplorer
Requires-Python: >=3.10
License-File: LICENSE
Dynamic: license-file
